{
  "id": "xkcd",
  "previewType": "card",
  "sampleResponse": {
    "num": 2934,
    "title": "AI Methodology",
    "alt": "I just trained a model to mass-produce peer reviews that say 'this methodology is not rigorous enough', so now I have a feedback loop that will eventually produce the most rigorous methodology possible.",
    "img_url": "https://imgs.xkcd.com/comics/ai_methodology.png",
    "year": 2025,
    "month": 11
  },
  "previewConfig": {
    "title": "xkcd #2934",
    "subtitle": "AI Methodology",
    "displayFields": ["num", "title", "alt", "img_url", "year", "month"]
  }
}